maskprocessor/__init__.py
maskprocessor/__main__.py
maskprocessor/__version__.py
maskprocessor/_version.py
maskprocessor/core.py
maskprocessor-0.0.5.dist-info/LICENSE
maskprocessor-0.0.5.dist-info/METADATA
maskprocessor-0.0.5.dist-info/WHEEL
maskprocessor-0.0.5.dist-info/entry_points.txt
maskprocessor-0.0.5.dist-info/top_level.txt
maskprocessor-0.0.5.dist-info/RECORD
