Metadata-Version: 2.1
Name: maskprocessor
Version: 0.0.5
Summary: Python maskprocessor implementation which inspired by hashcat maskprocessor
Home-page: https://github.com/Xvezda/python-maskprocessor
Author: Xvezda
Author-email: xvezda@naver.com
License: MIT
Project-URL: Repository, https://github.com/Xvezda/python-maskprocessor
Project-URL: Bug Reports, https://github.com/Xvezda/python-maskprocessor/issues
Keywords: hash,hashcat,maskprocessor,bruteforce
Platform: UNKNOWN
Classifier: Development Status :: 4 - Beta
Classifier: License :: OSI Approved :: MIT License
Classifier: Environment :: Console
Classifier: Topic :: Utilities
Classifier: Topic :: Security :: Cryptography
Classifier: Programming Language :: Python
Classifier: Programming Language :: Python :: 2
Classifier: Programming Language :: Python :: 2.7
Classifier: Programming Language :: Python :: 3
Classifier: Programming Language :: Python :: 3.5
Classifier: Programming Language :: Python :: 3.6
Classifier: Programming Language :: Python :: 3.7
Classifier: Programming Language :: Python :: 3.8
